dagviz/__init__.py
dagviz/abstract.py
dagviz/dagre.py
dagviz/istyle.py
dagviz/py.typed
dagviz/render.py
dagviz/style/__init__.py
dagviz/style/colors.py
dagviz/style/metro.py
dagviz-0.4.0.dist-info/LICENSE
dagviz-0.4.0.dist-info/METADATA
dagviz-0.4.0.dist-info/WHEEL
dagviz-0.4.0.dist-info/RECORD
