Metadata-Version: 2.1
Name: dagviz
Version: 0.4.0
Summary: Visualization for DAGs
Home-page: https://github.com/WimYedema/dagviz.git
License: Apache-2.0
Author: Wim Yedema
Author-email: wim.yedema@gmail.com
Requires-Python: >=3.7,<4.0
Classifier: License :: OSI Approved :: Apache Software License
Classifier: Operating System :: OS Independent
Classifier: Programming Language :: Python :: 3
Classifier: Programming Language :: Python :: 3.7
Classifier: Programming Language :: Python :: 3.8
Classifier: Programming Language :: Python :: 3.9
Classifier: Programming Language :: Python :: 3.10
Classifier: Programming Language :: Python :: 3.11
Requires-Dist: importlib-metadata (>=4.0,<5.0) ; python_version < "3.8"
Requires-Dist: networkx (>=2.5.1,<3.0.0)
Requires-Dist: svgwrite (>=1.4.1,<2.0.0)
Project-URL: Repository, https://github.com/WimYedema/dagviz.git
